odoo/addons/account_asset_compute_batch/README.rst
odoo/addons/account_asset_compute_batch/__init__.py
odoo/addons/account_asset_compute_batch/__manifest__.py
odoo/addons/account_asset_compute_batch/data/service_cron.xml
odoo/addons/account_asset_compute_batch/i18n/account_asset_compute_batch.pot
odoo/addons/account_asset_compute_batch/i18n/it.po
odoo/addons/account_asset_compute_batch/models/__init__.py
odoo/addons/account_asset_compute_batch/models/account_asset_compute_batch.py
odoo/addons/account_asset_compute_batch/models/account_asset_line.py
odoo/addons/account_asset_compute_batch/models/account_move.py
odoo/addons/account_asset_compute_batch/readme/CONTRIBUTORS.md
odoo/addons/account_asset_compute_batch/readme/DESCRIPTION.md
odoo/addons/account_asset_compute_batch/readme/USAGE.md
odoo/addons/account_asset_compute_batch/security/account_asset_security.xml
odoo/addons/account_asset_compute_batch/security/ir.model.access.csv
odoo/addons/account_asset_compute_batch/static/description/icon.png
odoo/addons/account_asset_compute_batch/static/description/index.html
odoo/addons/account_asset_compute_batch/tests/__init__.py
odoo/addons/account_asset_compute_batch/tests/test_account_asset_compute_batch.py
odoo/addons/account_asset_compute_batch/views/account_asset_compute_batch.xml
odoo/addons/account_asset_compute_batch/wizard/__init__.py
odoo/addons/account_asset_compute_batch/wizard/account_asset_compute.py
odoo/addons/account_asset_compute_batch/wizard/account_asset_compute.xml
odoo_addon_account_asset_compute_batch-18.0.1.0.0.6.dist-info/METADATA
odoo_addon_account_asset_compute_batch-18.0.1.0.0.6.dist-info/WHEEL
odoo_addon_account_asset_compute_batch-18.0.1.0.0.6.dist-info/top_level.txt
odoo_addon_account_asset_compute_batch-18.0.1.0.0.6.dist-info/RECORD
