Metadata-Version: 2.1
Name: odoo-addon-account_asset_compute_batch
Version: 18.0.1.0.0.6
Requires-Python: >=3.10
Requires-Dist: odoo-addon-account_asset_management==18.0.*
Requires-Dist: odoo==18.0.*
Summary: Assets - Compute Depre. in Batch
Home-page: https://github.com/OCA/account-financial-tools
License: AGPL-3
Author: Ecosoft, Odoo Community Association (OCA)
Author-email: support@odoo-community.org
Classifier: Programming Language :: Python
Classifier: Framework :: Odoo
Classifier: Framework :: Odoo :: 18.0
Classifier: License :: OSI Approved :: GNU Affero General Public License v3
